CHANGES.txt
LICENSE.txt
MANIFEST.in
README.md
README.txt
setup.py
ldap_test/__init__.py
ldap_test/ldap-test-server-0.0.3-SNAPSHOT-jar-with-dependencies.jar
ldap_test/server.py
ldap_test/test/__init__.py
ldap_test/test/tests.py
python_ldap_test.egg-info/PKG-INFO
python_ldap_test.egg-info/SOURCES.txt
python_ldap_test.egg-info/dependency_links.txt
python_ldap_test.egg-info/requires.txt
python_ldap_test.egg-info/top_level.txt