Metadata-Version: 1.0
Name: python-ldap-test
Version: 0.2.1
Summary: Tool for testing code speaking with LDAP server. Allows to easily configure and run an embedded, in-memory LDAP server. Uses UnboundID LDAP SDK through Py4J.
Home-page: https://github.com/zoldar/python-ldap-test/
Author: Adrian Gruntkowski
Author-email: adrian.gruntkowski@gmail.com
License: LICENSE.txt
Keywords: testing,tests,test,ldap
Platform: UNKNOWN
